odoo/addons/website_sale_ajaxify_cart/README.rst
odoo/addons/website_sale_ajaxify_cart/__init__.py
odoo/addons/website_sale_ajaxify_cart/__manifest__.py
odoo/addons/website_sale_ajaxify_cart/controllers/__init__.py
odoo/addons/website_sale_ajaxify_cart/controllers/main.py
odoo/addons/website_sale_ajaxify_cart/i18n/website_sale_ajaxify_cart.pot
odoo/addons/website_sale_ajaxify_cart/readme/DESCRIPTION.rst
odoo/addons/website_sale_ajaxify_cart/readme/USAGE.rst
odoo/addons/website_sale_ajaxify_cart/static/description/icon.png
odoo/addons/website_sale_ajaxify_cart/static/description/index.html
odoo/addons/website_sale_ajaxify_cart/static/src/js/website_sale.js
odoo/addons/website_sale_ajaxify_cart/tests/__init__.py
odoo/addons/website_sale_ajaxify_cart/tests/test_website_sale.py
odoo/addons/website_sale_ajaxify_cart/views/assets.xml
odoo/addons/website_sale_ajaxify_cart/views/templates.xml
odoo14_addon_website_sale_ajaxify_cart-14.0.1.0.1.dist-info/METADATA
odoo14_addon_website_sale_ajaxify_cart-14.0.1.0.1.dist-info/WHEEL
odoo14_addon_website_sale_ajaxify_cart-14.0.1.0.1.dist-info/top_level.txt
odoo14_addon_website_sale_ajaxify_cart-14.0.1.0.1.dist-info/RECORD
